{
  "id": "3861b41f-5072-46f2-88d1-e40e69b7882d",
  "prevId": "67c3684a-8681-4957-9bc6-9e9a06f60c6a",
  "version": "7",
  "dialect": "postgresql",
  "tables": {
    "public.api_keys": {
      "name": "api_keys",
      "schema": "",
      "columns": {
        "id": {
          "name": "id",
          "type": "uuid",
          "primaryKey": true,
          "notNull": true,
          "default": "gen_random_uuid()"
        },
        "project_id": {
          "name": "project_id",
          "type": "uuid",
          "primaryKey": false,
          "notNull": true
        },
        "key_hash": {
          "name": "key_hash",
          "type": "varchar(255)",
          "primaryKey": false,
          "notNull": true
        },
        "name": {
          "name": "name",
          "type": "varchar(128)",
          "primaryKey": false,
          "notNull": true
        },
        "type": {
          "name": "type",
          "type": "varchar(32)",
          "primaryKey": false,
          "notNull": true,
          "default": "'secret'"
        },
        "last_used_at": {
          "name": "last_used_at",
          "type": "timestamp with time zone",
          "primaryKey": false,
          "notNull": false
        },
        "created_at": {
          "name": "created_at",
          "type": "timestamp with time zone",
          "primaryKey": false,
          "notNull": true,
          "default": "now()"
        }
      },
      "indexes": {
        "api_keys_key_hash_idx": {
          "name": "api_keys_key_hash_idx",
          "columns": [
            {
              "expression": "key_hash",
              "isExpression": false,
              "asc": true,
              "nulls": "last"
            }
          ],
          "isUnique": false,
          "concurrently": false,
          "method": "btree",
          "with": {}
        }
      },
      "foreignKeys": {
        "api_keys_project_id_projects_id_fk": {
          "name": "api_keys_project_id_projects_id_fk",
          "tableFrom": "api_keys",
          "tableTo": "projects",
          "columnsFrom": [
            "project_id"
          ],
          "columnsTo": [
            "id"
          ],
          "onDelete": "cascade",
          "onUpdate": "no action"
        }
      },
      "compositePrimaryKeys": {},
      "uniqueConstraints": {
        "api_keys_key_hash_unique": {
          "name": "api_keys_key_hash_unique",
          "nullsNotDistinct": false,
          "columns": [
            "key_hash"
          ]
        }
      },
      "policies": {},
      "checkConstraints": {},
      "isRLSEnabled": false
    },
    "public.email_verification_tokens": {
      "name": "email_verification_tokens",
      "schema": "",
      "columns": {
        "id": {
          "name": "id",
          "type": "uuid",
          "primaryKey": true,
          "notNull": true,
          "default": "gen_random_uuid()"
        },
        "user_id": {
          "name": "user_id",
          "type": "uuid",
          "primaryKey": false,
          "notNull": true
        },
        "token_hash": {
          "name": "token_hash",
          "type": "varchar(255)",
          "primaryKey": false,
          "notNull": true
        },
        "expires_at": {
          "name": "expires_at",
          "type": "timestamp with time zone",
          "primaryKey": false,
          "notNull": true
        },
        "created_at": {
          "name": "created_at",
          "type": "timestamp with time zone",
          "primaryKey": false,
          "notNull": true,
          "default": "now()"
        }
      },
      "indexes": {},
      "foreignKeys": {
        "email_verification_tokens_user_id_users_id_fk": {
          "name": "email_verification_tokens_user_id_users_id_fk",
          "tableFrom": "email_verification_tokens",
          "tableTo": "users",
          "columnsFrom": [
            "user_id"
          ],
          "columnsTo": [
            "id"
          ],
          "onDelete": "cascade",
          "onUpdate": "no action"
        }
      },
      "compositePrimaryKeys": {},
      "uniqueConstraints": {
        "email_verification_tokens_token_hash_unique": {
          "name": "email_verification_tokens_token_hash_unique",
          "nullsNotDistinct": false,
          "columns": [
            "token_hash"
          ]
        }
      },
      "policies": {},
      "checkConstraints": {},
      "isRLSEnabled": false
    },
    "public.events": {
      "name": "events",
      "schema": "",
      "columns": {
        "id": {
          "name": "id",
          "type": "uuid",
          "primaryKey": true,
          "notNull": true,
          "default": "gen_random_uuid()"
        },
        "organization_id": {
          "name": "organization_id",
          "type": "uuid",
          "primaryKey": false,
          "notNull": true
        },
        "project_id": {
          "name": "project_id",
          "type": "uuid",
          "primaryKey": false,
          "notNull": true
        },
        "source": {
          "name": "source",
          "type": "varchar(256)",
          "primaryKey": false,
          "notNull": true
        },
        "type": {
          "name": "type",
          "type": "varchar(256)",
          "primaryKey": false,
          "notNull": true
        },
        "severity": {
          "name": "severity",
          "type": "varchar(32)",
          "primaryKey": false,
          "notNull": true
        },
        "correlation_id": {
          "name": "correlation_id",
          "type": "varchar(256)",
          "primaryKey": false,
          "notNull": false
        },
        "correlation": {
          "name": "correlation",
          "type": "jsonb",
          "primaryKey": false,
          "notNull": true,
          "default": "'{}'::jsonb"
        },
        "payload": {
          "name": "payload",
          "type": "jsonb",
          "primaryKey": false,
          "notNull": true,
          "default": "'{}'::jsonb"
        },
        "occurred_at": {
          "name": "occurred_at",
          "type": "timestamp with time zone",
          "primaryKey": false,
          "notNull": true
        },
        "created_at": {
          "name": "created_at",
          "type": "timestamp with time zone",
          "primaryKey": false,
          "notNull": true,
          "default": "now()"
        }
      },
      "indexes": {
        "idx_events_org_time": {
          "name": "idx_events_org_time",
          "columns": [
            {
              "expression": "organization_id",
              "isExpression": false,
              "asc": true,
              "nulls": "last"
            },
            {
              "expression": "occurred_at",
              "isExpression": false,
              "asc": true,
              "nulls": "last"
            }
          ],
          "isUnique": false,
          "concurrently": false,
          "method": "btree",
          "with": {}
        },
        "idx_events_project_time": {
          "name": "idx_events_project_time",
          "columns": [
            {
              "expression": "project_id",
              "isExpression": false,
              "asc": true,
              "nulls": "last"
            },
            {
              "expression": "occurred_at",
              "isExpression": false,
              "asc": true,
              "nulls": "last"
            }
          ],
          "isUnique": false,
          "concurrently": false,
          "method": "btree",
          "with": {}
        },
        "idx_events_correlation": {
          "name": "idx_events_correlation",
          "columns": [
            {
              "expression": "correlation_id",
              "isExpression": false,
              "asc": true,
              "nulls": "last"
            }
          ],
          "isUnique": false,
          "concurrently": false,
          "method": "btree",
          "with": {}
        },
        "idx_events_type_time": {
          "name": "idx_events_type_time",
          "columns": [
            {
              "expression": "organization_id",
              "isExpression": false,
              "asc": true,
              "nulls": "last"
            },
            {
              "expression": "type",
              "isExpression": false,
              "asc": true,
              "nulls": "last"
            },
            {
              "expression": "occurred_at",
              "isExpression": false,
              "asc": true,
              "nulls": "last"
            }
          ],
          "isUnique": false,
          "concurrently": false,
          "method": "btree",
          "with": {}
        },
        "idx_events_correlation_gin": {
          "name": "idx_events_correlation_gin",
          "columns": [
            {
              "expression": "correlation",
              "isExpression": false,
              "asc": true,
              "nulls": "last"
            }
          ],
          "isUnique": false,
          "concurrently": false,
          "method": "btree",
          "with": {}
        }
      },
      "foreignKeys": {
        "events_organization_id_organizations_id_fk": {
          "name": "events_organization_id_organizations_id_fk",
          "tableFrom": "events",
          "tableTo": "organizations",
          "columnsFrom": [
            "organization_id"
          ],
          "columnsTo": [
            "id"
          ],
          "onDelete": "cascade",
          "onUpdate": "no action"
        },
        "events_project_id_projects_id_fk": {
          "name": "events_project_id_projects_id_fk",
          "tableFrom": "events",
          "tableTo": "projects",
          "columnsFrom": [
            "project_id"
          ],
          "columnsTo": [
            "id"
          ],
          "onDelete": "cascade",
          "onUpdate": "no action"
        }
      },
      "compositePrimaryKeys": {},
      "uniqueConstraints": {},
      "policies": {},
      "checkConstraints": {},
      "isRLSEnabled": false
    },
    "public.incident_events": {
      "name": "incident_events",
      "schema": "",
      "columns": {
        "incident_id": {
          "name": "incident_id",
          "type": "uuid",
          "primaryKey": false,
          "notNull": true
        },
        "event_id": {
          "name": "event_id",
          "type": "uuid",
          "primaryKey": false,
          "notNull": true
        }
      },
      "indexes": {},
      "foreignKeys": {
        "incident_events_incident_id_incidents_id_fk": {
          "name": "incident_events_incident_id_incidents_id_fk",
          "tableFrom": "incident_events",
          "tableTo": "incidents",
          "columnsFrom": [
            "incident_id"
          ],
          "columnsTo": [
            "id"
          ],
          "onDelete": "cascade",
          "onUpdate": "no action"
        },
        "incident_events_event_id_events_id_fk": {
          "name": "incident_events_event_id_events_id_fk",
          "tableFrom": "incident_events",
          "tableTo": "events",
          "columnsFrom": [
            "event_id"
          ],
          "columnsTo": [
            "id"
          ],
          "onDelete": "cascade",
          "onUpdate": "no action"
        }
      },
      "compositePrimaryKeys": {
        "incident_events_incident_id_event_id_pk": {
          "name": "incident_events_incident_id_event_id_pk",
          "columns": [
            "incident_id",
            "event_id"
          ]
        }
      },
      "uniqueConstraints": {},
      "policies": {},
      "checkConstraints": {},
      "isRLSEnabled": false
    },
    "public.incidents": {
      "name": "incidents",
      "schema": "",
      "columns": {
        "id": {
          "name": "id",
          "type": "uuid",
          "primaryKey": true,
          "notNull": true,
          "default": "gen_random_uuid()"
        },
        "organization_id": {
          "name": "organization_id",
          "type": "uuid",
          "primaryKey": false,
          "notNull": true
        },
        "project_id": {
          "name": "project_id",
          "type": "uuid",
          "primaryKey": false,
          "notNull": true
        },
        "status": {
          "name": "status",
          "type": "varchar(32)",
          "primaryKey": false,
          "notNull": true,
          "default": "'OPEN'"
        },
        "severity": {
          "name": "severity",
          "type": "varchar(32)",
          "primaryKey": false,
          "notNull": true
        },
        "summary": {
          "name": "summary",
          "type": "text",
          "primaryKey": false,
          "notNull": true
        },
        "created_at": {
          "name": "created_at",
          "type": "timestamp with time zone",
          "primaryKey": false,
          "notNull": true,
          "default": "now()"
        },
        "updated_at": {
          "name": "updated_at",
          "type": "timestamp with time zone",
          "primaryKey": false,
          "notNull": true,
          "default": "now()"
        }
      },
      "indexes": {},
      "foreignKeys": {
        "incidents_organization_id_organizations_id_fk": {
          "name": "incidents_organization_id_organizations_id_fk",
          "tableFrom": "incidents",
          "tableTo": "organizations",
          "columnsFrom": [
            "organization_id"
          ],
          "columnsTo": [
            "id"
          ],
          "onDelete": "cascade",
          "onUpdate": "no action"
        },
        "incidents_project_id_projects_id_fk": {
          "name": "incidents_project_id_projects_id_fk",
          "tableFrom": "incidents",
          "tableTo": "projects",
          "columnsFrom": [
            "project_id"
          ],
          "columnsTo": [
            "id"
          ],
          "onDelete": "cascade",
          "onUpdate": "no action"
        }
      },
      "compositePrimaryKeys": {},
      "uniqueConstraints": {},
      "policies": {},
      "checkConstraints": {},
      "isRLSEnabled": false
    },
    "public.organization_members": {
      "name": "organization_members",
      "schema": "",
      "columns": {
        "id": {
          "name": "id",
          "type": "uuid",
          "primaryKey": true,
          "notNull": true,
          "default": "gen_random_uuid()"
        },
        "organization_id": {
          "name": "organization_id",
          "type": "uuid",
          "primaryKey": false,
          "notNull": true
        },
        "user_id": {
          "name": "user_id",
          "type": "uuid",
          "primaryKey": false,
          "notNull": true
        },
        "role": {
          "name": "role",
          "type": "varchar(32)",
          "primaryKey": false,
          "notNull": true
        },
        "created_at": {
          "name": "created_at",
          "type": "timestamp with time zone",
          "primaryKey": false,
          "notNull": true,
          "default": "now()"
        }
      },
      "indexes": {},
      "foreignKeys": {
        "organization_members_organization_id_organizations_id_fk": {
          "name": "organization_members_organization_id_organizations_id_fk",
          "tableFrom": "organization_members",
          "tableTo": "organizations",
          "columnsFrom": [
            "organization_id"
          ],
          "columnsTo": [
            "id"
          ],
          "onDelete": "cascade",
          "onUpdate": "no action"
        },
        "organization_members_user_id_users_id_fk": {
          "name": "organization_members_user_id_users_id_fk",
          "tableFrom": "organization_members",
          "tableTo": "users",
          "columnsFrom": [
            "user_id"
          ],
          "columnsTo": [
            "id"
          ],
          "onDelete": "cascade",
          "onUpdate": "no action"
        }
      },
      "compositePrimaryKeys": {},
      "uniqueConstraints": {},
      "policies": {},
      "checkConstraints": {},
      "isRLSEnabled": false
    },
    "public.organizations": {
      "name": "organizations",
      "schema": "",
      "columns": {
        "id": {
          "name": "id",
          "type": "uuid",
          "primaryKey": true,
          "notNull": true,
          "default": "gen_random_uuid()"
        },
        "name": {
          "name": "name",
          "type": "varchar(256)",
          "primaryKey": false,
          "notNull": true
        },
        "plan": {
          "name": "plan",
          "type": "varchar(64)",
          "primaryKey": false,
          "notNull": true,
          "default": "'FREE'"
        },
        "created_at": {
          "name": "created_at",
          "type": "timestamp with time zone",
          "primaryKey": false,
          "notNull": true,
          "default": "now()"
        },
        "updated_at": {
          "name": "updated_at",
          "type": "timestamp with time zone",
          "primaryKey": false,
          "notNull": true,
          "default": "now()"
        }
      },
      "indexes": {},
      "foreignKeys": {},
      "compositePrimaryKeys": {},
      "uniqueConstraints": {},
      "policies": {},
      "checkConstraints": {},
      "isRLSEnabled": false
    },
    "public.password_reset_tokens": {
      "name": "password_reset_tokens",
      "schema": "",
      "columns": {
        "id": {
          "name": "id",
          "type": "uuid",
          "primaryKey": true,
          "notNull": true,
          "default": "gen_random_uuid()"
        },
        "user_id": {
          "name": "user_id",
          "type": "uuid",
          "primaryKey": false,
          "notNull": true
        },
        "token_hash": {
          "name": "token_hash",
          "type": "varchar(255)",
          "primaryKey": false,
          "notNull": true
        },
        "expires_at": {
          "name": "expires_at",
          "type": "timestamp with time zone",
          "primaryKey": false,
          "notNull": true
        },
        "created_at": {
          "name": "created_at",
          "type": "timestamp with time zone",
          "primaryKey": false,
          "notNull": true,
          "default": "now()"
        }
      },
      "indexes": {},
      "foreignKeys": {
        "password_reset_tokens_user_id_users_id_fk": {
          "name": "password_reset_tokens_user_id_users_id_fk",
          "tableFrom": "password_reset_tokens",
          "tableTo": "users",
          "columnsFrom": [
            "user_id"
          ],
          "columnsTo": [
            "id"
          ],
          "onDelete": "cascade",
          "onUpdate": "no action"
        }
      },
      "compositePrimaryKeys": {},
      "uniqueConstraints": {
        "password_reset_tokens_token_hash_unique": {
          "name": "password_reset_tokens_token_hash_unique",
          "nullsNotDistinct": false,
          "columns": [
            "token_hash"
          ]
        }
      },
      "policies": {},
      "checkConstraints": {},
      "isRLSEnabled": false
    },
    "public.projects": {
      "name": "projects",
      "schema": "",
      "columns": {
        "id": {
          "name": "id",
          "type": "uuid",
          "primaryKey": true,
          "notNull": true,
          "default": "gen_random_uuid()"
        },
        "organization_id": {
          "name": "organization_id",
          "type": "uuid",
          "primaryKey": false,
          "notNull": true
        },
        "name": {
          "name": "name",
          "type": "varchar(512)",
          "primaryKey": false,
          "notNull": true
        },
        "environment": {
          "name": "environment",
          "type": "varchar(64)",
          "primaryKey": false,
          "notNull": true,
          "default": "'PRODUCTION'"
        },
        "created_at": {
          "name": "created_at",
          "type": "timestamp with time zone",
          "primaryKey": false,
          "notNull": true,
          "default": "now()"
        },
        "updated_at": {
          "name": "updated_at",
          "type": "timestamp with time zone",
          "primaryKey": false,
          "notNull": true,
          "default": "now()"
        }
      },
      "indexes": {},
      "foreignKeys": {
        "projects_organization_id_organizations_id_fk": {
          "name": "projects_organization_id_organizations_id_fk",
          "tableFrom": "projects",
          "tableTo": "organizations",
          "columnsFrom": [
            "organization_id"
          ],
          "columnsTo": [
            "id"
          ],
          "onDelete": "cascade",
          "onUpdate": "no action"
        }
      },
      "compositePrimaryKeys": {},
      "uniqueConstraints": {},
      "policies": {},
      "checkConstraints": {},
      "isRLSEnabled": false
    },
    "public.users": {
      "name": "users",
      "schema": "",
      "columns": {
        "id": {
          "name": "id",
          "type": "uuid",
          "primaryKey": true,
          "notNull": true,
          "default": "gen_random_uuid()"
        },
        "email": {
          "name": "email",
          "type": "varchar(256)",
          "primaryKey": false,
          "notNull": true
        },
        "name": {
          "name": "name",
          "type": "varchar(256)",
          "primaryKey": false,
          "notNull": true
        },
        "password_hash": {
          "name": "password_hash",
          "type": "varchar(255)",
          "primaryKey": false,
          "notNull": true
        },
        "email_verified": {
          "name": "email_verified",
          "type": "boolean",
          "primaryKey": false,
          "notNull": true,
          "default": false
        },
        "created_at": {
          "name": "created_at",
          "type": "timestamp with time zone",
          "primaryKey": false,
          "notNull": true,
          "default": "now()"
        },
        "updated_at": {
          "name": "updated_at",
          "type": "timestamp with time zone",
          "primaryKey": false,
          "notNull": true,
          "default": "now()"
        }
      },
      "indexes": {},
      "foreignKeys": {},
      "compositePrimaryKeys": {},
      "uniqueConstraints": {
        "users_email_unique": {
          "name": "users_email_unique",
          "nullsNotDistinct": false,
          "columns": [
            "email"
          ]
        }
      },
      "policies": {},
      "checkConstraints": {},
      "isRLSEnabled": false
    },
    "public.webhook_endpoints": {
      "name": "webhook_endpoints",
      "schema": "",
      "columns": {
        "id": {
          "name": "id",
          "type": "uuid",
          "primaryKey": true,
          "notNull": true,
          "default": "gen_random_uuid()"
        },
        "project_id": {
          "name": "project_id",
          "type": "uuid",
          "primaryKey": false,
          "notNull": true
        },
        "name": {
          "name": "name",
          "type": "varchar(128)",
          "primaryKey": false,
          "notNull": true
        },
        "token": {
          "name": "token",
          "type": "varchar(64)",
          "primaryKey": false,
          "notNull": true
        },
        "secret": {
          "name": "secret",
          "type": "varchar(255)",
          "primaryKey": false,
          "notNull": true
        },
        "created_at": {
          "name": "created_at",
          "type": "timestamp with time zone",
          "primaryKey": false,
          "notNull": true,
          "default": "now()"
        }
      },
      "indexes": {
        "idx_webhook_endpoints_token": {
          "name": "idx_webhook_endpoints_token",
          "columns": [
            {
              "expression": "token",
              "isExpression": false,
              "asc": true,
              "nulls": "last"
            }
          ],
          "isUnique": false,
          "concurrently": false,
          "method": "btree",
          "with": {}
        },
        "idx_webhook_endpoints_project": {
          "name": "idx_webhook_endpoints_project",
          "columns": [
            {
              "expression": "project_id",
              "isExpression": false,
              "asc": true,
              "nulls": "last"
            }
          ],
          "isUnique": false,
          "concurrently": false,
          "method": "btree",
          "with": {}
        }
      },
      "foreignKeys": {
        "webhook_endpoints_project_id_projects_id_fk": {
          "name": "webhook_endpoints_project_id_projects_id_fk",
          "tableFrom": "webhook_endpoints",
          "tableTo": "projects",
          "columnsFrom": [
            "project_id"
          ],
          "columnsTo": [
            "id"
          ],
          "onDelete": "cascade",
          "onUpdate": "no action"
        }
      },
      "compositePrimaryKeys": {},
      "uniqueConstraints": {
        "webhook_endpoints_token_unique": {
          "name": "webhook_endpoints_token_unique",
          "nullsNotDistinct": false,
          "columns": [
            "token"
          ]
        }
      },
      "policies": {},
      "checkConstraints": {},
      "isRLSEnabled": false
    }
  },
  "enums": {},
  "schemas": {},
  "sequences": {},
  "roles": {},
  "policies": {},
  "views": {},
  "_meta": {
    "columns": {},
    "schemas": {},
    "tables": {}
  }
}